{
  "name": "Webots khw-2hv",
  "version": 1,
  "motorgroups": {
    "l_arm": [
      "l_shoulder_x",
      "l_shoulder_y",
      "l_elbow_y"
    ],
    "r_arm": [
      "r_shoulder_x",
      "r_shoulder_y",
      "r_elbow_y"
    ],
    "arms": [
      "l_arm",
      "r_arm"
    ]
  },
  "motors": {
    "l_shoulder_x": {
      "offset": -90.0,
      "type": "MX-28",
      "id": "Left_Shoulder",
      "angle_limit": [
        -105,
        110
      ],
      "orientation": "direct"
    },
    "r_shoulder_x": {
      "offset": 90.0,
      "type": "MX-28",
      "id": "Right_Shoulder",
      "angle_limit": [
        -110,
        105
      ],
      "orientation": "indirect"
    },
    "l_shoulder_y": {
      "offset": 90,
      "type": "MX-28",
      "id": "Left_Arm1",
      "angle_limit": [
        -120,
        155
      ],
      "orientation": "direct"
    },
    "r_shoulder_y": {
      "offset": 90,
      "type": "MX-28",
      "id": "Right_Arm1",
      "angle_limit": [
        -155,
        120
      ],
      "orientation": "indirect"
    },
    "l_elbow_y": {
      "offset": 0.0,
      "type": "MX-28",
      "id": "Left_Hand",
      "angle_limit": [
        -148,
        1
      ],
      "orientation": "direct"
    },
    "r_elbow_y": {
      "offset": 0.0,
      "type": "MX-28",
      "id": "Right_Hand",
      "angle_limit": [
        -1,
        148
      ],
      "orientation": "indirect"
    }
  }
}
